MANIFEST.in
README.md
setup.py
pyload_utils.egg-info/PKG-INFO
pyload_utils.egg-info/SOURCES.txt
pyload_utils.egg-info/dependency_links.txt
pyload_utils.egg-info/entry_points.txt
pyload_utils.egg-info/top_level.txt
pyloadutils/__init__.py
pyloadutils/check_incomplete.py
pyloadutils/del_404.py
pyloadutils/deloffline.py
pyloadutils/merger.py
pyloadutils/pyload.py
pyloadutils/restart.py