Metadata-Version: 1.1
Name: pyload-utils
Version: 0.1.1
Summary: Some usefull utilities for the pyload download manager
Home-page: https://github.com/thammi/pyload-utils
Author: Thammi
Author-email: thammi@chaossource.net
License: GPLv3
Keywords: pyload
Platform: UNKNOWN
Classifier: Programming Language :: Python :: 3
Classifier: Environment :: Console
Classifier: License :: OSI Approved :: GNU General Public License (GPL)
